{
    "categorias":[
        {
            "id_categorias": 1,
            "titulo": "cabañas",
            "descripcion": "Casas de madera para 2 personas",
            "url_imagen": "https://images.unsplash.com/photo-1601918774946-25832a4be0d6?crop=entropy&cs=tinysrgb&fm=jpg&ixlib=rb-1.2.1&q=60&raw_url=true&ixid=MnwxMjA3fDB8MHxzZWFyY2h8Mnx8Y2FiYSVDMyVCMWFzfGVufDB8fDB8fA%3D%3D&auto=format&fit=crop&w=500"
        },
        {
            "id_categorias": 2,
            "titulo": "casa temporaria",
            "descripcion": "Casas de alquiler temporario cerca de ciudades",
            "url_imagen": "https://images.unsplash.com/photo-1572120360610-d971b9d7767c?crop=entropy&cs=tinysrgb&fm=jpg&ixlib=rb-1.2.1&q=80&raw_url=true&ixid=MnwxMjA3fDB8MHxwaG90by1wYWdlfHx8fGVufDB8fHx8&auto=format&fit=crop&w=870"
        },
        {
            "id_categorias": 3,
            "titulo": "casa de playa",
            "descripcion": "Casas playeras con salida al mar",
            "url_imagen": "https://images.unsplash.com/photo-1499793983690-e29da59ef1c2?crop=entropy&cs=tinysrgb&fm=jpg&ixlib=rb-1.2.1&q=60&raw_url=true&ixid=MnwxMjA3fDB8MHxzZWFyY2h8MXx8Y2FzYSUyMGRlJTIwcGxheWF8ZW58MHx8MHx8&auto=format&fit=crop&w=500"
        },
        {
            "id_categorias": 4,
            "titulo": "hostal",
            "descripcion": "Casas de alquiler compartido",
            "url_imagen": "https://images.unsplash.com/photo-1566073771259-6a8506099945?crop=entropy&cs=tinysrgb&fm=jpg&ixlib=rb-1.2.1&q=60&raw_url=true&ixid=MnwxMjA3fDB8MHxzZWFyY2h8Nnx8aG9zdGVsfGVufDB8fDB8fA%3D%3D&auto=format&fit=crop&w=500"
        }
    ]
}